ucam_observe/__init__.py
ucam_observe/django.py
ucam_observe/gunicorn.py
ucam_observe/logging_config.py
ucam_observe-0.2.1.dist-info/METADATA
ucam_observe-0.2.1.dist-info/WHEEL
ucam_observe-0.2.1.dist-info/RECORD
