Metadata-Version: 2.3
Name: ucam_observe
Version: 0.2.1
Summary: Python library to aid consistent configuration of logging, metrics (future) and tracing (further in future). Packaging and wiring existing open tooling to work effortlessly on UIS DevOps managed cloud infrastructure.
License: MIT
Requires-Python: >=3.9.1,<4.0.0
Classifier: License :: OSI Approved :: MIT License
Classifier: Programming Language :: Python :: 3
Classifier: Programming Language :: Python :: 3.10
Classifier: Programming Language :: Python :: 3.11
Classifier: Programming Language :: Python :: 3.12
Classifier: Programming Language :: Python :: 3.13
Provides-Extra: django
Requires-Dist: django-structlog (>=8.0.0,<9.0.0) ; extra == "django"
Requires-Dist: structlog (>=24.1.0,<25.0.0)
